odoo/addons/stock_location_template/README.rst
odoo/addons/stock_location_template/__init__.py
odoo/addons/stock_location_template/__manifest__.py
odoo/addons/stock_location_template/i18n/stock_location_template.pot
odoo/addons/stock_location_template/models/__init__.py
odoo/addons/stock_location_template/models/stock_location.py
odoo/addons/stock_location_template/models/stock_location_template.py
odoo/addons/stock_location_template/readme/CONTRIBUTORS.rst
odoo/addons/stock_location_template/readme/DESCRIPTION.rst
odoo/addons/stock_location_template/readme/USAGE.rst
odoo/addons/stock_location_template/security/ir.model.access.csv
odoo/addons/stock_location_template/static/description/icon.png
odoo/addons/stock_location_template/static/description/index.html
odoo/addons/stock_location_template/tests/__init__.py
odoo/addons/stock_location_template/tests/test_stock_location_template.py
odoo/addons/stock_location_template/views/stock_location_template_views.xml
odoo/addons/stock_location_template/views/stock_location_views.xml
odoo12_addon_stock_location_template-12.0.1.0.2.dist-info/METADATA
odoo12_addon_stock_location_template-12.0.1.0.2.dist-info/WHEEL
odoo12_addon_stock_location_template-12.0.1.0.2.dist-info/top_level.txt
odoo12_addon_stock_location_template-12.0.1.0.2.dist-info/RECORD
